{"artist": "Austrian Death Machine", "album": "Total Brutal", "mbid": "f61e20ce-7772-4a3a-9368-d17f5f5dbe92", "cover_path": "/covers/austrian_death_machine_-_total_brutal.jpg", "tracks": [{"name": "Hello California", "energy": 0.346, "valence": 0.568, "danceability": 0.616, "tempo": 86.166}, {"name": "Get to the Choppa", "energy": 0.975, "valence": 0.437, "danceability": 0.222, "tempo": 189.811}, {"name": "Rubber Baby Buggy Bumpers", "energy": 0.978, "valence": 0.537, "danceability": 0.33, "tempo": 194.533}, {"name": "All of the Songs Sound the Same", "energy": 0.341, "valence": 0.0, "danceability": 0.0, "tempo": 0.0}, {"name": "I Am a Cybernetic Organism, Living Tissue Over (Metal) Endoskeleton", "energy": 0.968, "valence": 0.21, "danceability": 0.201, "tempo": 181.63}, {"name": "Come With Me If You Want to Live", "energy": 0.984, "valence": 0.53, "danceability": 0.273, "tempo": 194.47}, {"name": "What It's Like to Be a Singer at Band Practice", "energy": 0.595, "valence": 0.426, "danceability": 0.497, "tempo": 171.369}, {"name": "Who Is Your Daddy, and What Does He Do?", "energy": 0.917, "valence": 0.167, "danceability": 0.211, "tempo": 186.083}, {"name": "You Have Just Been Erased", "energy": 0.928, "valence": 0.476, "danceability": 0.354, "tempo": 92.896}, {"name": "Broo-Tall Song Idea", "energy": 0.498, "valence": 0.649, "danceability": 0.756, "tempo": 44.33}]}
