{"artist": "Billy Cobham", "album": "A Funky Thide of Sings", "mbid": "7d01bdf2-17a1-4dce-be03-0b5ffc644cb3", "cover_path": "/covers/billy_cobham_-_a_funky_thide_of_sings.jpg", "tracks": [{"name": "Panhandler", "energy": 0.791, "valence": 0.729, "danceability": 0.625, "tempo": 121.272}, {"name": "Sorcery", "energy": 0.843, "valence": 0.624, "danceability": 0.438, "tempo": 111.763}, {"name": "A Funky Thide of Sings", "energy": 0.769, "valence": 0.881, "danceability": 0.663, "tempo": 132.103}, {"name": "Thinking of You", "energy": 0.825, "valence": 0.732, "danceability": 0.531, "tempo": 118.068}, {"name": "Some Skunk Funk", "energy": 0.854, "valence": 0.785, "danceability": 0.596, "tempo": 134.335}, {"name": "Light at the End of the Tunnel", "energy": 0.755, "valence": 0.888, "danceability": 0.48, "tempo": 115.784}, {"name": "A Funky Kind of Thing", "energy": 0.69, "valence": 0.0795, "danceability": 0.518, "tempo": 136.975}, {"name": "Moody Modes", "energy": 0.378, "valence": 0.247, "danceability": 0.366, "tempo": 90.595}]}
