{"artist": "Bob Dylan", "album": "Playlist: The Very Best of Bob Dylan '70s", "mbid": "626df837-ae96-4d97-903b-60a855502c58", "cover_path": "/covers/bob_dylan_-_playlist_the_very_best_of_bob_dylan_70s.jpg", "tracks": [{"name": "If Not for You", "energy": 0.593, "valence": 0.884, "danceability": 0.663, "tempo": 139.481}, {"name": "You Ain’t Goin’ Nowhere", "energy": 0.326, "valence": 0.573, "danceability": 0.482, "tempo": 155.337}, {"name": "Forever Young", "energy": 0.461, "valence": 0.338, "danceability": 0.49, "tempo": 135.068}, {"name": "Knockin’ on Heaven’s Door", "energy": 0.396, "valence": 0.229, "danceability": 0.513, "tempo": 140.208}, {"name": "On a Night Like This", "energy": 0.785, "valence": 0.933, "danceability": 0.56, "tempo": 138.778}, {"name": "Precious Angel", "energy": 0.703, "valence": 0.812, "danceability": 0.736, "tempo": 122.575}, {"name": "Tangled Up in Blue", "energy": 0.661, "valence": 0.554, "danceability": 0.421, "tempo": 100.965}, {"name": "Gotta Serve Somebody", "energy": 0.526, "valence": 0.811, "danceability": 0.81, "tempo": 95.23}]}
