{"artist": "Boysetsfire", "album": "Tomorrow Come Today", "mbid": "44c567d0-13ec-4afd-8a65-8cdc1a8aa5bc", "cover_path": "/covers/boysetsfire_-_tomorrow_come_today.jpg", "tracks": [{"name": "Eviction Article", "energy": 0.975, "valence": 0.289, "danceability": 0.594, "tempo": 115.819}, {"name": "Last Year’s Nest", "energy": 0.882, "valence": 0.377, "danceability": 0.567, "tempo": 114.618}, {"name": "Full Color Guilt", "energy": 0.93, "valence": 0.501, "danceability": 0.386, "tempo": 173.821}, {"name": "Bathory’s Sainthood", "energy": 0.832, "valence": 0.178, "danceability": 0.503, "tempo": 159.991}, {"name": "Dying on Principle", "energy": 0.973, "valence": 0.577, "danceability": 0.556, "tempo": 120.781}, {"name": "Handful of Redemption", "energy": 0.947, "valence": 0.419, "danceability": 0.508, "tempo": 163.731}, {"name": "Release the Dogs", "energy": 0.977, "valence": 0.379, "danceability": 0.386, "tempo": 195.991}, {"name": "Foundations to Burn", "energy": 0.928, "valence": 0.549, "danceability": 0.487, "tempo": 177.672}, {"name": "Management vs. Labor", "energy": 0.92, "valence": 0.411, "danceability": 0.479, "tempo": 167.719}, {"name": "High Wire Escape Artist", "energy": 0.652, "valence": 0.426, "danceability": 0.487, "tempo": 163.849}]}
