{"artist": "Bruce Springsteen", "album": "18 Tracks", "mbid": "cae5c99c-79b7-49a7-9742-714905364e0c", "cover_path": "/covers/bruce_springsteen_-_18_tracks.jpg", "tracks": [{"name": "Growin’ Up", "energy": 0.74, "valence": 0.69, "danceability": 0.614, "tempo": 132.301}, {"name": "Seaside Bar Song", "energy": 0.903, "valence": 0.704, "danceability": 0.307, "tempo": 167.407}, {"name": "Rendezvous", "energy": 0.898, "valence": 0.831, "danceability": 0.472, "tempo": 127.602}, {"name": "Hearts of Stone", "energy": 0.526, "valence": 0.483, "danceability": 0.412, "tempo": 130.088}, {"name": "Where the Bands Are", "energy": 0.99, "valence": 0.518, "danceability": 0.342, "tempo": 140.842}, {"name": "I Wanna Be With You", "energy": 0.892, "valence": 0.899, "danceability": 0.476, "tempo": 115.913}, {"name": "Born in the U.S.A.", "energy": 0.952, "valence": 0.584, "danceability": 0.398, "tempo": 122.093}, {"name": "My Love Will Not Let You Down", "energy": 0.911, "valence": 0.792, "danceability": 0.409, "tempo": 153.283}, {"name": "Lion’s Den", "energy": 0.93, "valence": 0.243, "danceability": 0.409, "tempo": 134.26}]}
