{"artist": "Camila", "album": "Dejarte de amar", "mbid": "b0a99d0b-b28d-4bec-b40b-dbbc0747c7a6", "cover_path": "/covers/camila_-_dejarte_de_amar.jpg", "tracks": [{"name": "Mientes", "energy": 0.592, "valence": 0.312, "danceability": 0.331, "tempo": 170.436}, {"name": "Entre tus alas", "energy": 0.531, "valence": 0.0953, "danceability": 0.206, "tempo": 180.666}, {"name": "Bésame", "energy": 0.384, "valence": 0.168, "danceability": 0.256, "tempo": 175.543}, {"name": "Maya", "energy": 0.867, "valence": 0.403, "danceability": 0.444, "tempo": 151.035}, {"name": "Dejarte de amar", "energy": 0.715, "valence": 0.219, "danceability": 0.516, "tempo": 160.462}, {"name": "Aléjate de mí", "energy": 0.536, "valence": 0.25, "danceability": 0.457, "tempo": 145.681}, {"name": "Me voy", "energy": 0.549, "valence": 0.159, "danceability": 0.459, "tempo": 174.388}, {"name": "Nada", "energy": 0.383, "valence": 0.229, "danceability": 0.454, "tempo": 173.346}, {"name": "De qué me sirve la vida", "energy": 0.468, "valence": 0.179, "danceability": 0.411, "tempo": 149.399}, {"name": "Restos de abril", "energy": 0.306, "valence": 0.311, "danceability": 0.35, "tempo": 159.755}]}
