{"artist": "Canon", "album": "Mad Haven", "mbid": "70486efa-e30a-4813-b489-a65d02fdaf26", "cover_path": "/covers/canon_-_mad_haven.jpg", "tracks": [{"name": "Mad Haven", "energy": 0.757, "valence": 0.2, "danceability": 0.382, "tempo": 169.688}, {"name": "How We Do It", "energy": 0.862, "valence": 0.399, "danceability": 0.537, "tempo": 76.031}, {"name": "Walk With Me", "energy": 0.883, "valence": 0.395, "danceability": 0.591, "tempo": 170.197}, {"name": "Different", "energy": 0.68, "valence": 0.591, "danceability": 0.667, "tempo": 76.756}, {"name": "Relations", "energy": 0.911, "valence": 0.643, "danceability": 0.734, "tempo": 90.562}, {"name": "Lotto", "energy": 0.797, "valence": 0.537, "danceability": 0.734, "tempo": 135.026}, {"name": "What It Sounds Like", "energy": 0.928, "valence": 0.414, "danceability": 0.464, "tempo": 150.264}, {"name": "Special", "energy": 0.786, "valence": 0.341, "danceability": 0.51, "tempo": 168.976}, {"name": "Full Plates", "energy": 0.882, "valence": 0.334, "danceability": 0.561, "tempo": 140.166}, {"name": "Out of Tune", "energy": 0.962, "valence": 0.496, "danceability": 0.608, "tempo": 140.04}]}
