{"artist": "Cold War Kids", "album": "Loyalty to Loyalty", "mbid": "f7bba251-4154-4ed6-aeb0-6c12c5c0cf22", "cover_path": "/covers/cold_war_kids_-_loyalty_to_loyalty.jpg", "tracks": [{"name": "Against Privacy", "energy": 0.516, "valence": 0.273, "danceability": 0.396, "tempo": 152.667}, {"name": "Mexican Dogs", "energy": 0.783, "valence": 0.313, "danceability": 0.479, "tempo": 93.149}, {"name": "Every Valley Is Not a Lake", "energy": 0.814, "valence": 0.57, "danceability": 0.405, "tempo": 104.67}, {"name": "Something Is Not Right With Me", "energy": 0.659, "valence": 0.636, "danceability": 0.555, "tempo": 120.688}, {"name": "Welcome to the Occupation", "energy": 0.71, "valence": 0.401, "danceability": 0.48, "tempo": 119.736}, {"name": "Golden Gate Jumpers", "energy": 0.422, "valence": 0.125, "danceability": 0.419, "tempo": 144.3}, {"name": "Avalanche in B", "energy": 0.293, "valence": 0.14, "danceability": 0.4, "tempo": 135.683}, {"name": "I've Seen Enough", "energy": 0.741, "valence": 0.408, "danceability": 0.537, "tempo": 89.483}, {"name": "Every Man I Fall For", "energy": 0.405, "valence": 0.211, "danceability": 0.473, "tempo": 84.59}, {"name": "Dreams Old Men Dream", "energy": 0.683, "valence": 0.238, "danceability": 0.429, "tempo": 119.599}]}
