{"artist": "David Archuleta", "album": "David Archuleta", "mbid": "baa1f9ac-e48f-42af-8750-d0f8ce2c6cc5", "cover_path": "/covers/david_archuleta_-_david_archuleta.jpg", "tracks": [{"name": "Crush", "energy": 0.664, "valence": 0.487, "danceability": 0.57, "tempo": 162.084}, {"name": "Touch My Hand", "energy": 0.731, "valence": 0.405, "danceability": 0.687, "tempo": 109.006}, {"name": "Barriers", "energy": 0.583, "valence": 0.612, "danceability": 0.642, "tempo": 137.907}, {"name": "My Hands", "energy": 0.816, "valence": 0.416, "danceability": 0.534, "tempo": 82.508}, {"name": "A Little Too Not Over You", "energy": 0.694, "valence": 0.538, "danceability": 0.531, "tempo": 163.978}, {"name": "You Can", "energy": 0.521, "valence": 0.242, "danceability": 0.472, "tempo": 151.011}, {"name": "Running", "energy": 0.757, "valence": 0.509, "danceability": 0.564, "tempo": 89.994}, {"name": "Desperate", "energy": 0.81, "valence": 0.236, "danceability": 0.525, "tempo": 134.053}, {"name": "To Be with You", "energy": 0.216, "valence": 0.176, "danceability": 0.389, "tempo": 75.261}, {"name": "Don't Let Go", "energy": 0.703, "valence": 0.378, "danceability": 0.564, "tempo": 137.972}]}
