{"artist": "Dio", "album": "Dio at Donington UK: Live 1983 & 1987", "mbid": "68d1e74c-1b3a-4718-850c-4d26d2907b19", "cover_path": null, "tracks": [{"name": "Stand Up and Shout", "energy": 0.936, "valence": 0.337, "danceability": 0.485, "tempo": 109.374}, {"name": "Straight Through the Heart", "energy": 0.947, "valence": 0.571, "danceability": 0.484, "tempo": 94.517}, {"name": "Rainbow in the Dark", "energy": 0.947, "valence": 0.612, "danceability": 0.512, "tempo": 117.461}, {"name": "Holy Diver", "energy": 0.901, "valence": 0.109, "danceability": 0.476, "tempo": 91.955}]}
