{"artist": "Donny Osmond", "album": "The Donny Osmond Album", "mbid": "3424632f-1358-411d-85bd-3312f644c400", "cover_path": "/covers/donny_osmond_-_the_donny_osmond_album.jpg", "tracks": [{"name": "Sweet and Innocent", "energy": 0.786, "valence": 0.969, "danceability": 0.762, "tempo": 125.524}, {"name": "I’m Your Puppet", "energy": 0.523, "valence": 0.67, "danceability": 0.619, "tempo": 108.336}, {"name": "Hey Little Girl", "energy": 0.792, "valence": 0.962, "danceability": 0.67, "tempo": 100.329}, {"name": "Don’t Say No", "energy": 0.526, "valence": 0.498, "danceability": 0.634, "tempo": 129.428}, {"name": "So Shy", "energy": 0.869, "valence": 0.724, "danceability": 0.67, "tempo": 129.657}, {"name": "Lollipops, Lace and Lipstick", "energy": 0.706, "valence": 0.961, "danceability": 0.714, "tempo": 139.616}, {"name": "Flirtin’", "energy": 0.856, "valence": 0.892, "danceability": 0.533, "tempo": 101.912}, {"name": "Burning Bridges", "energy": 0.677, "valence": 0.777, "danceability": 0.562, "tempo": 95.922}, {"name": "Wake Up, Little Susie", "energy": 0.745, "valence": 0.956, "danceability": 0.781, "tempo": 137.966}]}
