{"artist": "Down", "album": "Down IV, Part I: The Purple EP", "mbid": "12301c9f-770c-4de7-b101-0fe2dde5e6f2", "cover_path": null, "tracks": [{"name": "Levitation", "energy": 0.931, "valence": 0.248, "danceability": 0.31, "tempo": 147.845}, {"name": "Witchtripper", "energy": 0.964, "valence": 0.418, "danceability": 0.348, "tempo": 138.024}, {"name": "Open Coffins", "energy": 0.88, "valence": 0.39, "danceability": 0.363, "tempo": 84.857}, {"name": "The Curse", "energy": 0.932, "valence": 0.212, "danceability": 0.274, "tempo": 140.186}, {"name": "This Work Is Timeless", "energy": 0.937, "valence": 0.361, "danceability": 0.23, "tempo": 101.088}, {"name": "Misfortune Teller", "energy": 0.452, "valence": 0.102, "danceability": 0.369, "tempo": 121.072}]}
