{"artist": "Elvis Presley", "album": "Elvis’ Christmas Album", "mbid": "2e427dea-3565-4ba6-963b-2b2e271b0d53", "cover_path": "/covers/elvis_presley_-_elvis_christmas_album.jpg", "tracks": [{"name": "Santa Claus Is Back in Town", "energy": 0.485, "valence": 0.539, "danceability": 0.42, "tempo": 94.65}, {"name": "White Christmas", "energy": 0.0677, "valence": 0.34, "danceability": 0.49, "tempo": 94.065}, {"name": "Here Comes Santa Claus (Right Down Santa Claus Lane)", "energy": 0.235, "valence": 0.834, "danceability": 0.573, "tempo": 79.578}, {"name": "I'll Be Home for Christmas", "energy": 0.0311, "valence": 0.128, "danceability": 0.491, "tempo": 75.503}, {"name": "Blue Christmas", "energy": 0.27, "valence": 0.58, "danceability": 0.465, "tempo": 94.519}, {"name": "Santa Bring My Baby Back (to Me)", "energy": 0.399, "valence": 0.961, "danceability": 0.619, "tempo": 94.36}, {"name": "Oh Little Town of Bethlehem", "energy": 0.0406, "valence": 0.218, "danceability": 0.324, "tempo": 99.286}, {"name": "Silent Night", "energy": 0.0314, "valence": 0.176, "danceability": 0.27, "tempo": 135.473}, {"name": "(There'll Be) Peace in the Valley (for Me)", "energy": 0.0334, "valence": 0.242, "danceability": 0.305, "tempo": 65.042}, {"name": "I Believe", "energy": 0.133, "valence": 0.208, "danceability": 0.317, "tempo": 97.259}]}
