{"artist": "England Dan & John Ford Coley", "album": "Some Things Don’t Come Easy", "mbid": "768bc875-f689-4fd1-bf9f-f67b2918afff", "cover_path": "/covers/england_dan_john_ford_coley_-_some_things_dont_come_easy.jpg", "tracks": [{"name": "Some Things Don’t Come Easy", "energy": 0.484, "valence": 0.583, "danceability": 0.692, "tempo": 108.724}, {"name": "If the World Ran Out of Love Tonight", "energy": 0.409, "valence": 0.464, "danceability": 0.537, "tempo": 60.206}, {"name": "You Can’t Dance", "energy": 0.664, "valence": 0.966, "danceability": 0.673, "tempo": 148.393}, {"name": "Who’s Lonely Now", "energy": 0.154, "valence": 0.526, "danceability": 0.478, "tempo": 83.514}, {"name": "Hold Me", "energy": 0.228, "valence": 0.362, "danceability": 0.569, "tempo": 116.21}, {"name": "We’ll Never Have to Say Goodbye Again", "energy": 0.344, "valence": 0.605, "danceability": 0.516, "tempo": 112.224}, {"name": "Lovin’ Somebody on a Rainy Night", "energy": 0.596, "valence": 0.868, "danceability": 0.672, "tempo": 137.304}, {"name": "Beyond the Tears", "energy": 0.259, "valence": 0.187, "danceability": 0.51, "tempo": 146.18}, {"name": "Calling for You Again", "energy": 0.562, "valence": 0.932, "danceability": 0.721, "tempo": 137.767}, {"name": "Wanting You Desperately", "energy": 0.365, "valence": 0.658, "danceability": 0.718, "tempo": 113.447}]}
