{"artist": "Fiction Family", "album": "Fiction Family Reunion", "mbid": "dc63262d-da8c-4408-82a0-6f982b18e2eb", "cover_path": "/covers/fiction_family_-_fiction_family_reunion.jpg", "tracks": [{"name": "Avalon", "energy": 0.727, "valence": 0.325, "danceability": 0.508, "tempo": 81.039}, {"name": "Guilt", "energy": 0.816, "valence": 0.828, "danceability": 0.569, "tempo": 81.463}, {"name": "Up Against the Wall", "energy": 0.561, "valence": 0.284, "danceability": 0.547, "tempo": 125.827}, {"name": "Give Me Back My Girl", "energy": 0.83, "valence": 0.88, "danceability": 0.515, "tempo": 174.012}, {"name": "Damaged", "energy": 0.459, "valence": 0.307, "danceability": 0.468, "tempo": 140.805}, {"name": "God Badge", "energy": 0.644, "valence": 0.268, "danceability": 0.551, "tempo": 147.996}, {"name": "Never Call", "energy": 0.454, "valence": 0.549, "danceability": 0.571, "tempo": 120.839}, {"name": "Just Rob Me", "energy": 0.864, "valence": 0.924, "danceability": 0.388, "tempo": 140.226}, {"name": "Reality Calls", "energy": 0.347, "valence": 0.734, "danceability": 0.595, "tempo": 128.648}, {"name": "Fools Gold", "energy": 0.374, "valence": 0.437, "danceability": 0.484, "tempo": 138.509}]}
