{"artist": "Grand Funk Railroad", "album": "On Time", "mbid": "798a3c50-b701-4e96-889b-e61adc1837bb", "cover_path": "/covers/grand_funk_railroad_-_on_time.jpg", "tracks": [{"name": "Are You Ready", "energy": 0.736, "valence": 0.922, "danceability": 0.557, "tempo": 80.653}, {"name": "Anybody’s Answer", "energy": 0.546, "valence": 0.215, "danceability": 0.34, "tempo": 155.842}, {"name": "Time Machine", "energy": 0.497, "valence": 0.835, "danceability": 0.644, "tempo": 109.44}, {"name": "High on a Horse", "energy": 0.786, "valence": 0.509, "danceability": 0.477, "tempo": 128.345}, {"name": "T.N.U.C.", "energy": 0.812, "valence": 0.378, "danceability": 0.305, "tempo": 163.698}, {"name": "Into the Sun", "energy": 0.549, "valence": 0.309, "danceability": 0.439, "tempo": 122.918}, {"name": "Heartbreaker", "energy": 0.777, "valence": 0.554, "danceability": 0.198, "tempo": 79.394}, {"name": "Call Yourself a Man", "energy": 0.752, "valence": 0.423, "danceability": 0.592, "tempo": 140.849}, {"name": "Can’t Be Too Long", "energy": 0.401, "valence": 0.404, "danceability": 0.327, "tempo": 166.195}, {"name": "Ups and Downs", "energy": 0.509, "valence": 0.577, "danceability": 0.425, "tempo": 144.334}]}
