{"artist": "Grover Washington, Jr.", "album": "Soulful Strut", "mbid": "8f1804f0-14f8-4e9b-a160-9a8fcd8c3784", "cover_path": "/covers/grover_washington_jr_-_soulful_strut.jpg", "tracks": [{"name": "Soulful Strut", "energy": 0.772, "valence": 0.822, "danceability": 0.561, "tempo": 185.864}, {"name": "Can You Stop The Rain", "energy": 0.47, "valence": 0.299, "danceability": 0.527, "tempo": 119.891}, {"name": "Play That Groove For Me", "energy": 0.752, "valence": 0.736, "danceability": 0.625, "tempo": 106.501}, {"name": "Bordertown", "energy": 0.593, "valence": 0.841, "danceability": 0.746, "tempo": 103.991}, {"name": "I Can Count The Times", "energy": 0.656, "valence": 0.467, "danceability": 0.491, "tempo": 161.743}, {"name": "Village Groove", "energy": 0.768, "valence": 0.604, "danceability": 0.656, "tempo": 97.917}, {"name": "Headman's Haunt", "energy": 0.693, "valence": 0.557, "danceability": 0.6, "tempo": 106.873}, {"name": "Poacher Man", "energy": 0.703, "valence": 0.487, "danceability": 0.652, "tempo": 137.922}, {"name": "Mystical Force", "energy": 0.656, "valence": 0.507, "danceability": 0.589, "tempo": 137.73}, {"name": "Uptown", "energy": 0.646, "valence": 0.56, "danceability": 0.677, "tempo": 111.931}]}
