{"artist": "Heart", "album": "Little Queen", "mbid": "97ee0dea-7f27-4508-b523-0bb70747445b", "cover_path": "/covers/heart_-_little_queen.jpg", "tracks": [{"name": "Barracuda", "energy": 0.691, "valence": 0.667, "danceability": 0.547, "tempo": 137.148}, {"name": "Love Alive", "energy": 0.335, "valence": 0.225, "danceability": 0.542, "tempo": 91.047}, {"name": "Sylvan Song", "energy": 0.274, "valence": 0.16, "danceability": 0.312, "tempo": 87.987}, {"name": "Dream of the Archer", "energy": 0.285, "valence": 0.144, "danceability": 0.475, "tempo": 137.917}, {"name": "Kick It Out", "energy": 0.726, "valence": 0.674, "danceability": 0.402, "tempo": 149.272}, {"name": "Little Queen", "energy": 0.361, "valence": 0.671, "danceability": 0.674, "tempo": 99.095}, {"name": "Treat Me Well", "energy": 0.107, "valence": 0.166, "danceability": 0.403, "tempo": 132.509}, {"name": "Say Hello", "energy": 0.468, "valence": 0.962, "danceability": 0.525, "tempo": 172.237}, {"name": "Cry to Me", "energy": 0.0631, "valence": 0.406, "danceability": 0.506, "tempo": 122.899}, {"name": "Go On Cry", "energy": 0.26, "valence": 0.171, "danceability": 0.409, "tempo": 127.749}]}
