{"artist": "Jane Wiedlin", "album": "Jane Wiedlin", "mbid": "b0b0fa9f-2617-4cd7-a3d3-4c1437643917", "cover_path": "/covers/jane_wiedlin_-_jane_wiedlin.jpg", "tracks": [{"name": "Blue Kiss", "energy": 0.582, "valence": 0.961, "danceability": 0.76, "tempo": 128.37}, {"name": "Somebody's Going to Get Into This House", "energy": 0.873, "valence": 0.704, "danceability": 0.564, "tempo": 133.134}, {"name": "One Hundred Years of Solitude", "energy": 0.622, "valence": 0.496, "danceability": 0.586, "tempo": 131.627}]}
