{"artist": "Jeezy", "album": "Seen It All: The Autobiography", "mbid": "7071c133-2565-431f-86c4-8a878a8d36d2", "cover_path": "/covers/jeezy_-_seen_it_all_the_autobiography.jpg", "tracks": [{"name": "1/4 Block", "energy": 0.714, "valence": 0.346, "danceability": 0.707, "tempo": 108.1}, {"name": "What You Say", "energy": 0.816, "valence": 0.77, "danceability": 0.758, "tempo": 101.933}, {"name": "Enough", "energy": 0.762, "valence": 0.461, "danceability": 0.642, "tempo": 165.149}, {"name": "Holy Ghost", "energy": 0.728, "valence": 0.274, "danceability": 0.629, "tempo": 157.914}, {"name": "Me OK", "energy": 0.763, "valence": 0.64, "danceability": 0.766, "tempo": 140.546}, {"name": "Been Getting Money", "energy": 0.719, "valence": 0.25, "danceability": 0.686, "tempo": 94.982}, {"name": "Seen It All", "energy": 0.833, "valence": 0.545, "danceability": 0.711, "tempo": 106.094}, {"name": "Win Is a Win", "energy": 0.754, "valence": 0.0382, "danceability": 0.248, "tempo": 82.419}, {"name": "Beautiful", "energy": 0.777, "valence": 0.404, "danceability": 0.563, "tempo": 76.086}, {"name": "Beez Like", "energy": 0.751, "valence": 0.478, "danceability": 0.619, "tempo": 172.068}]}
