{"artist": "John Gary", "album": "So Tenderly / A Little Bit of Heaven", "mbid": "eafbd4ff-3952-4623-9ee0-ef4aeb0bca37", "cover_path": null, "tracks": [{"name": "Tenderly", "energy": 0.276, "valence": 0.0813, "danceability": 0.142, "tempo": 86.533}, {"name": "If You Love Me", "energy": 0.265, "valence": 0.184, "danceability": 0.247, "tempo": 80.893}, {"name": "Take My Love", "energy": 0.298, "valence": 0.216, "danceability": 0.154, "tempo": 172.703}, {"name": "Danny Boy", "energy": 0.171, "valence": 0.11, "danceability": 0.166, "tempo": 174.816}, {"name": "Brown Eyed Baby Boy", "energy": 0.233, "valence": 0.141, "danceability": 0.258, "tempo": 106.402}, {"name": "Smilin' Through", "energy": 0.166, "valence": 0.15, "danceability": 0.166, "tempo": 83.392}, {"name": "Come to Me, Bend to Me", "energy": 0.265, "valence": 0.129, "danceability": 0.19, "tempo": 80.366}, {"name": "The Song of Coo Coo", "energy": 0.31, "valence": 0.239, "danceability": 0.37, "tempo": 66.909}, {"name": "Red Rosey Bush", "energy": 0.189, "valence": 0.315, "danceability": 0.216, "tempo": 82.366}, {"name": "Something Simple", "energy": 0.181, "valence": 0.17, "danceability": 0.271, "tempo": 80.264}]}
