{"artist": "John Hiatt", "album": "Stolen Moments", "mbid": "e8ff04d6-cdca-3d97-a26b-79f2e0742719", "cover_path": "/covers/john_hiatt_-_stolen_moments.jpg", "tracks": [{"name": "Real Fine Love", "energy": 0.499, "valence": 0.844, "danceability": 0.667, "tempo": 102.259}, {"name": "Seven Little Indians", "energy": 0.471, "valence": 0.849, "danceability": 0.581, "tempo": 97.285}, {"name": "Child of the Wild Blue Yonder", "energy": 0.708, "valence": 0.938, "danceability": 0.622, "tempo": 89.175}, {"name": "Back of My Mind", "energy": 0.432, "valence": 0.542, "danceability": 0.38, "tempo": 159.945}, {"name": "Stolen Moments", "energy": 0.532, "valence": 0.723, "danceability": 0.736, "tempo": 117.133}, {"name": "Bring Back Your Love to Me", "energy": 0.42, "valence": 0.621, "danceability": 0.707, "tempo": 101.483}, {"name": "The Rest of the Dream", "energy": 0.588, "valence": 0.897, "danceability": 0.594, "tempo": 138.19}, {"name": "Thirty Years of Tears", "energy": 0.331, "valence": 0.284, "danceability": 0.58, "tempo": 50.712}, {"name": "Rock Back Billy", "energy": 0.632, "valence": 0.868, "danceability": 0.441, "tempo": 170.075}, {"name": "Listening to Old Voices", "energy": 0.421, "valence": 0.589, "danceability": 0.64, "tempo": 88.028}]}
