{"artist": "KIDZ BOP Kids", "album": "Kidz Bop Halloween Hits!", "mbid": "5b96d60b-fe6d-494b-9992-0b4e09157edd", "cover_path": "/covers/kidz_bop_kids_-_kidz_bop_halloween_hits.jpg", "tracks": [{"name": "Thriller", "energy": 0.973, "valence": 0.685, "danceability": 0.698, "tempo": 119.079}, {"name": "Disturbia", "energy": 0.85, "valence": 0.818, "danceability": 0.751, "tempo": 125.023}, {"name": "Candy Girl", "energy": 0.892, "valence": 0.788, "danceability": 0.729, "tempo": 103.984}, {"name": "Witch Doctor", "energy": 0.924, "valence": 0.963, "danceability": 0.684, "tempo": 139.97}, {"name": "Ghostbusters", "energy": 0.93, "valence": 0.596, "danceability": 0.692, "tempo": 120.026}, {"name": "Werewolves of London", "energy": 0.783, "valence": 0.859, "danceability": 0.627, "tempo": 104.246}, {"name": "The Addams Family", "energy": 0.636, "valence": 0.779, "danceability": 0.364, "tempo": 180.232}, {"name": "Monster Mash", "energy": 0.809, "valence": 0.639, "danceability": 0.638, "tempo": 136.088}, {"name": "Scooby Doo, Where Are You?", "energy": 0.952, "valence": 0.961, "danceability": 0.55, "tempo": 135.977}, {"name": "A Nightmare on My Street", "energy": 0.826, "valence": 0.622, "danceability": 0.664, "tempo": 170.372}]}
