{"artist": "Kidz Bop Kids", "album": "KIDZ BOP 5", "mbid": "0e920212-0666-48e3-8644-65eadb4f43e5", "cover_path": "/covers/kidz_bop_kids_-_kidz_bop_5.jpg", "tracks": [{"name": "Crazy in Love", "energy": 0.891, "valence": 0.497, "danceability": 0.725, "tempo": 100.016}, {"name": "Hey Ya!", "energy": 0.875, "valence": 0.937, "danceability": 0.715, "tempo": 159.091}, {"name": "Are You Happy Now?", "energy": 0.629, "valence": 0.538, "danceability": 0.494, "tempo": 179.544}, {"name": "Invisible", "energy": 0.745, "valence": 0.51, "danceability": 0.632, "tempo": 110.057}, {"name": "It’s My Life", "energy": 0.544, "valence": 0.883, "danceability": 0.732, "tempo": 126.286}, {"name": "Here Without You", "energy": 0.44, "valence": 0.238, "danceability": 0.473, "tempo": 143.976}, {"name": "Girls and Boys", "energy": 0.651, "valence": 0.675, "danceability": 0.665, "tempo": 135.475}, {"name": "So Yesterday", "energy": 0.509, "valence": 0.669, "danceability": 0.596, "tempo": 77.887}, {"name": "Calling All Angels", "energy": 0.387, "valence": 0.596, "danceability": 0.685, "tempo": 71.936}]}
