{"artist": "Kris Kristofferson", "album": "This Old Road", "mbid": "d6367498-0b2d-4995-8244-b205d0247085", "cover_path": "/covers/kris_kristofferson_-_this_old_road.jpg", "tracks": [{"name": "This Old Road", "energy": 0.409, "valence": 0.391, "danceability": 0.56, "tempo": 135.87}, {"name": "Pilgrim’s Progress", "energy": 0.316, "valence": 0.558, "danceability": 0.767, "tempo": 93.064}, {"name": "The Last Thing to Go", "energy": 0.279, "valence": 0.438, "danceability": 0.512, "tempo": 105.372}, {"name": "Wild American", "energy": 0.244, "valence": 0.4, "danceability": 0.728, "tempo": 77.787}, {"name": "In the News", "energy": 0.298, "valence": 0.461, "danceability": 0.635, "tempo": 77.237}, {"name": "The Burden of Freedom", "energy": 0.211, "valence": 0.211, "danceability": 0.623, "tempo": 122.206}, {"name": "Chase the Feeling", "energy": 0.722, "valence": 0.663, "danceability": 0.498, "tempo": 159.283}, {"name": "Holy Creation", "energy": 0.16, "valence": 0.315, "danceability": 0.616, "tempo": 112.395}, {"name": "The Show Goes On", "energy": 0.378, "valence": 0.842, "danceability": 0.803, "tempo": 112.362}, {"name": "Thank You for a Life", "energy": 0.237, "valence": 0.416, "danceability": 0.601, "tempo": 96.813}]}
