{"artist": "Lecrae", "album": "Anomaly", "mbid": "cba91fda-449c-40d4-9334-419fb6eab57a", "cover_path": "/covers/lecrae_-_anomaly.jpg", "tracks": [{"name": "Outsiders", "energy": 0.657, "valence": 0.0392, "danceability": 0.473, "tempo": 140.035}, {"name": "Welcome to America", "energy": 0.921, "valence": 0.506, "danceability": 0.749, "tempo": 124.913}, {"name": "Say I Won’t", "energy": 0.683, "valence": 0.742, "danceability": 0.813, "tempo": 127.993}, {"name": "Nuthin", "energy": 0.69, "valence": 0.362, "danceability": 0.848, "tempo": 102.448}, {"name": "Fear", "energy": 0.609, "valence": 0.183, "danceability": 0.631, "tempo": 140.029}, {"name": "Anomaly", "energy": 0.695, "valence": 0.285, "danceability": 0.652, "tempo": 128.966}, {"name": "Timepiece", "energy": 0.552, "valence": 0.464, "danceability": 0.578, "tempo": 151.851}, {"name": "Dirty Water", "energy": 0.599, "valence": 0.333, "danceability": 0.81, "tempo": 67.492}, {"name": "Wish", "energy": 0.751, "valence": 0.194, "danceability": 0.693, "tempo": 137.046}, {"name": "Runners", "energy": 0.697, "valence": 0.64, "danceability": 0.824, "tempo": 101.973}]}
