{"artist": "Lee Michaels", "album": "Nice Day for Something", "mbid": "43d4ce69-04c2-4f2b-9572-ab81bfdcc33b", "cover_path": "/covers/lee_michaels_-_nice_day_for_something.jpg", "tracks": [{"name": "Your Breath Is Bleeding", "energy": 0.385, "valence": 0.926, "danceability": 0.68, "tempo": 102.7}, {"name": "Same Old Song", "energy": 0.561, "valence": 0.923, "danceability": 0.691, "tempo": 139.195}, {"name": "So Hard", "energy": 0.227, "valence": 0.465, "danceability": 0.559, "tempo": 135.215}, {"name": "High Wind", "energy": 0.545, "valence": 0.94, "danceability": 0.723, "tempo": 118.739}, {"name": "Olson Arrives at Two Fifty-Five", "energy": 0.423, "valence": 0.342, "danceability": 0.551, "tempo": 139.117}, {"name": "The Other Day (The Other Way)", "energy": 0.519, "valence": 0.813, "danceability": 0.75, "tempo": 109.839}, {"name": "Rock & Roll Community", "energy": 0.332, "valence": 0.821, "danceability": 0.655, "tempo": 83.463}, {"name": "Bell", "energy": 0.368, "valence": 0.174, "danceability": 0.647, "tempo": 117.527}, {"name": "Went Saw Mama", "energy": 0.403, "valence": 0.882, "danceability": 0.867, "tempo": 91.797}, {"name": "Nothing Matters (But It Doesn't Matter)", "energy": 0.623, "valence": 0.783, "danceability": 0.609, "tempo": 119.322}]}
