{"artist": "Nat King Cole", "album": "My Fair Lady", "mbid": "3fe7d388-f2ac-4e73-b68c-1a15d197a9f9", "cover_path": "/covers/nat_king_cole_-_my_fair_lady.jpg", "tracks": [{"name": "With a Little Bit of Luck", "energy": 0.688, "valence": 0.836, "danceability": 0.469, "tempo": 139.175}, {"name": "I Could Have Danced All Night", "energy": 0.427, "valence": 0.305, "danceability": 0.313, "tempo": 136.975}, {"name": "The Rain in Spain", "energy": 0.493, "valence": 0.457, "danceability": 0.606, "tempo": 113.751}, {"name": "On the Street Where You Live", "energy": 0.421, "valence": 0.316, "danceability": 0.242, "tempo": 71.897}, {"name": "I’m an Ordinary Man", "energy": 0.668, "valence": 0.521, "danceability": 0.468, "tempo": 76.39}, {"name": "Get Me to the Church on Time", "energy": 0.651, "valence": 0.52, "danceability": 0.594, "tempo": 118.61}, {"name": "Show Me", "energy": 0.293, "valence": 0.133, "danceability": 0.249, "tempo": 111.154}, {"name": "I’ve Grown Accustomed to Her Face", "energy": 0.305, "valence": 0.206, "danceability": 0.215, "tempo": 74.519}, {"name": "You Did It", "energy": 0.682, "valence": 0.485, "danceability": 0.586, "tempo": 74.911}, {"name": "Wouldn’t It Be Loverly", "energy": 0.366, "valence": 0.319, "danceability": 0.394, "tempo": 95.919}]}
