{"artist": "Nonpoint", "album": "Recoil", "mbid": "a0f0924c-731a-43c2-89f2-42181c76d7c9", "cover_path": "/covers/nonpoint_-_recoil.jpg", "tracks": [{"name": "The Same", "energy": 0.919, "valence": 0.451, "danceability": 0.376, "tempo": 156.124}, {"name": "The Truth", "energy": 0.881, "valence": 0.439, "danceability": 0.423, "tempo": 158.049}, {"name": "Broken Bones", "energy": 0.959, "valence": 0.475, "danceability": 0.4, "tempo": 96.054}, {"name": "Wait", "energy": 0.817, "valence": 0.144, "danceability": 0.27, "tempo": 66.093}, {"name": "Rabia", "energy": 0.949, "valence": 0.315, "danceability": 0.594, "tempo": 114.976}, {"name": "Done It Anyway", "energy": 0.956, "valence": 0.547, "danceability": 0.419, "tempo": 146.274}, {"name": "In the Air Tonight", "energy": 0.812, "valence": 0.181, "danceability": 0.556, "tempo": 99.935}, {"name": "Move Now", "energy": 0.936, "valence": 0.416, "danceability": 0.459, "tempo": 112.493}, {"name": "Peace of Mind", "energy": 0.883, "valence": 0.394, "danceability": 0.492, "tempo": 134.12}, {"name": "Past It All", "energy": 0.858, "valence": 0.346, "danceability": 0.217, "tempo": 79.043}]}
