{"artist": "Olivia Newton‐John", "album": "Warm and Tender", "mbid": "245ffb2a-b6bd-4196-9d2a-09b188e05df5", "cover_path": "/covers/olivia_newtonjohn_-_warm_and_tender.jpg", "tracks": [{"name": "Jenny Rebecca", "energy": 0.173, "valence": 0.194, "danceability": 0.299, "tempo": 137.196}, {"name": "Rocking", "energy": 0.152, "valence": 0.152, "danceability": 0.224, "tempo": 99.555}, {"name": "The Way You Look Tonight", "energy": 0.155, "valence": 0.062, "danceability": 0.274, "tempo": 76.579}, {"name": "Lullaby Lullaby My Lovely One", "energy": 0.0444, "valence": 0.166, "danceability": 0.464, "tempo": 77.496}, {"name": "You’ll Never Walk Alone", "energy": 0.0952, "valence": 0.0779, "danceability": 0.121, "tempo": 69.623}, {"name": "Sleep My Princess", "energy": 0.0402, "valence": 0.215, "danceability": 0.403, "tempo": 113.175}, {"name": "The Flower That Shattered the Stone", "energy": 0.13, "valence": 0.198, "danceability": 0.5, "tempo": 96.795}, {"name": "Twinkle Twinkle Little Star", "energy": 0.0728, "valence": 0.0897, "danceability": 0.425, "tempo": 97.585}, {"name": "Warm and Tender", "energy": 0.184, "valence": 0.18, "danceability": 0.57, "tempo": 99.975}, {"name": "Rock a Bye Baby", "energy": 0.0691, "valence": 0.145, "danceability": 0.485, "tempo": 89.074}]}
