{"artist": "Pat Metheny Group", "album": "American Garage", "mbid": "f5af64db-4459-4e65-989f-9af9f704b46b", "cover_path": "/covers/pat_metheny_group_-_american_garage.jpg", "tracks": [{"name": "(Cross the) Heartland", "energy": 0.456, "valence": 0.299, "danceability": 0.34, "tempo": 99.484}, {"name": "Airstream", "energy": 0.311, "valence": 0.258, "danceability": 0.509, "tempo": 132.053}, {"name": "The Search", "energy": 0.341, "valence": 0.372, "danceability": 0.374, "tempo": 103.473}, {"name": "American Garage", "energy": 0.565, "valence": 0.756, "danceability": 0.495, "tempo": 137.589}, {"name": "The Epic", "energy": 0.366, "valence": 0.192, "danceability": 0.325, "tempo": 153.068}]}
