{"artist": "Playboi Carti", "album": "Playboi Carti", "mbid": "ed678e9a-de0f-4490-846d-b10f1518d3ec", "cover_path": "/covers/playboi_carti_-_playboi_carti.jpg", "tracks": [{"name": "Location", "energy": 0.79, "valence": 0.375, "danceability": 0.717, "tempo": 125.981}, {"name": "Magnolia", "energy": 0.581, "valence": 0.438, "danceability": 0.791, "tempo": 162.99}, {"name": "Lookin", "energy": 0.57, "valence": 0.412, "danceability": 0.827, "tempo": 148.119}, {"name": "wokeuplikethis*", "energy": 0.62, "valence": 0.478, "danceability": 0.785, "tempo": 78.476}, {"name": "Let It Go", "energy": 0.53, "valence": 0.55, "danceability": 0.685, "tempo": 157.012}, {"name": "Half & Half", "energy": 0.496, "valence": 0.145, "danceability": 0.899, "tempo": 127.046}, {"name": "New Choppa", "energy": 0.605, "valence": 0.425, "danceability": 0.772, "tempo": 128.162}, {"name": "Other Shit", "energy": 0.47, "valence": 0.423, "danceability": 0.841, "tempo": 133.026}, {"name": "NO. 9", "energy": 0.607, "valence": 0.391, "danceability": 0.885, "tempo": 137.881}, {"name": "dothatshit!", "energy": 0.744, "valence": 0.451, "danceability": 0.745, "tempo": 162.965}]}
