{"artist": "Rare Earth", "album": "Ma", "mbid": "651bc01c-9da2-4d4b-935b-b82241a10bf5", "cover_path": "/covers/rare_earth_-_ma.jpg", "tracks": [{"name": "Ma", "energy": 0.461, "valence": 0.862, "danceability": 0.709, "tempo": 95.132}, {"name": "Big John Is My Name", "energy": 0.723, "valence": 0.901, "danceability": 0.687, "tempo": 89.24}, {"name": "Smiling Faces Sometimes", "energy": 0.492, "valence": 0.749, "danceability": 0.712, "tempo": 90.218}, {"name": "Hum Along And Dance", "energy": 0.822, "valence": 0.801, "danceability": 0.613, "tempo": 102.665}, {"name": "Come With Me", "energy": 0.165, "valence": 0.259, "danceability": 0.588, "tempo": 119.76}]}
