{"artist": "Robert Gordon with Link Wray", "album": "Robert Gordon With Link Wray", "mbid": "fca8d8fe-9148-4a5f-ad5d-83a2e0e92d91", "cover_path": "/covers/robert_gordon_with_link_wray_-_robert_gordon_with_link_wray.jpg", "tracks": [{"name": "Red Hot", "energy": 0.884, "valence": 0.959, "danceability": 0.474, "tempo": 189.534}, {"name": "I Sure Miss You", "energy": 0.453, "valence": 0.737, "danceability": 0.372, "tempo": 141.339}, {"name": "Summertime Blues", "energy": 0.668, "valence": 0.969, "danceability": 0.666, "tempo": 144.593}, {"name": "Boppin’ the Blues", "energy": 0.674, "valence": 0.88, "danceability": 0.483, "tempo": 186.961}, {"name": "Sweet Surrender", "energy": 0.466, "valence": 0.884, "danceability": 0.356, "tempo": 133.37}, {"name": "Flyin’ Saucers Rock & Roll", "energy": 0.883, "valence": 0.802, "danceability": 0.393, "tempo": 178.431}, {"name": "The Fool", "energy": 0.629, "valence": 0.882, "danceability": 0.623, "tempo": 143.031}, {"name": "It’s in the Bottle", "energy": 0.426, "valence": 0.391, "danceability": 0.476, "tempo": 82.026}, {"name": "Woman (You’re My Woman)", "energy": 0.748, "valence": 0.502, "danceability": 0.554, "tempo": 123.075}, {"name": "Is This the Way", "energy": 0.348, "valence": 0.783, "danceability": 0.608, "tempo": 109.646}]}
