{"artist": "Roger Creager", "album": "Road Show", "mbid": "49038441-01b9-456f-bfa5-f23ce5f40ac6", "cover_path": "/covers/roger_creager_-_road_show.jpg", "tracks": [{"name": "Road Show", "energy": 0.827, "valence": 0.499, "danceability": 0.445, "tempo": 167.974}, {"name": "Where the Gringos Don't Go", "energy": 0.614, "valence": 0.553, "danceability": 0.509, "tempo": 157.894}, {"name": "River Song", "energy": 0.628, "valence": 0.27, "danceability": 0.593, "tempo": 78.986}, {"name": "Different Than I'm Feeling Right Now", "energy": 0.703, "valence": 0.781, "danceability": 0.624, "tempo": 152.028}, {"name": "I Love You When I'm Drunk", "energy": 0.703, "valence": 0.465, "danceability": 0.638, "tempo": 117.012}, {"name": "Forever in Your Eyes", "energy": 0.479, "valence": 0.18, "danceability": 0.592, "tempo": 77.911}, {"name": "Little Bit of Them All", "energy": 0.832, "valence": 0.697, "danceability": 0.446, "tempo": 164.19}]}
