{"artist": "Ruben Studdard", "album": "Soulful", "mbid": "71a723ff-5846-4642-ae5c-5cd52d0d3f5f", "cover_path": "/covers/ruben_studdard_-_soulful.jpg", "tracks": [{"name": "Sorry 2004", "energy": 0.472, "valence": 0.462, "danceability": 0.721, "tempo": 129.964}, {"name": "No Ruben", "energy": 0.778, "valence": 0.465, "danceability": 0.627, "tempo": 85.402}, {"name": "How Can You Mend a Broken Heart", "energy": 0.46, "valence": 0.416, "danceability": 0.422, "tempo": 178.078}, {"name": "Take the Shot", "energy": 0.685, "valence": 0.621, "danceability": 0.43, "tempo": 59.804}, {"name": "What Is Sexy", "energy": 0.659, "valence": 0.751, "danceability": 0.771, "tempo": 91.445}, {"name": "What If", "energy": 0.463, "valence": 0.77, "danceability": 0.728, "tempo": 144.045}, {"name": "Superstar", "energy": 0.425, "valence": 0.154, "danceability": 0.363, "tempo": 112.374}, {"name": "Can I Get Your Attention", "energy": 0.585, "valence": 0.788, "danceability": 0.699, "tempo": 86.347}, {"name": "For All We Know", "energy": 0.443, "valence": 0.0753, "danceability": 0.486, "tempo": 109.922}, {"name": "Play Our Song", "energy": 0.622, "valence": 0.874, "danceability": 0.801, "tempo": 122.558}]}
