{"artist": "Run‐D.M.C.", "album": "Back From Hell", "mbid": "ce2fd798-d9eb-49b8-8fe9-8f27da39340c", "cover_path": null, "tracks": [{"name": "Sucker D.J.’s", "energy": 0.769, "valence": 0.964, "danceability": 0.747, "tempo": 107.19}, {"name": "The Ave.", "energy": 0.781, "valence": 0.725, "danceability": 0.688, "tempo": 95.247}, {"name": "What’s It All About", "energy": 0.827, "valence": 0.475, "danceability": 0.814, "tempo": 109.09}, {"name": "Bob Your Head", "energy": 0.771, "valence": 0.73, "danceability": 0.807, "tempo": 160.26}, {"name": "Faces", "energy": 0.722, "valence": 0.684, "danceability": 0.591, "tempo": 109.647}, {"name": "Kick the Frama Lama Lama", "energy": 0.903, "valence": 0.704, "danceability": 0.717, "tempo": 174.66}, {"name": "Pause", "energy": 0.764, "valence": 0.57, "danceability": 0.747, "tempo": 106.12}, {"name": "Word Is Born", "energy": 0.631, "valence": 0.75, "danceability": 0.54, "tempo": 111.92}, {"name": "Back From Hell", "energy": 0.673, "valence": 0.866, "danceability": 0.702, "tempo": 200.062}, {"name": "Don’t Stop", "energy": 0.758, "valence": 0.441, "danceability": 0.805, "tempo": 108.102}]}
