{"artist": "Stevie Ray Vaughan and Double Trouble", "album": "In the Beginning", "mbid": "f5447c0a-98b7-41c0-898d-0f0cac5a73c7", "cover_path": "/covers/stevie_ray_vaughan_and_double_trouble_-_in_the_beginning.jpg", "tracks": [{"name": "In the Open", "energy": 0.968, "valence": 0.538, "danceability": 0.412, "tempo": 167.447}, {"name": "Slide Thing", "energy": 0.938, "valence": 0.799, "danceability": 0.35, "tempo": 118.568}, {"name": "They Call Me Guitar Hurricane", "energy": 0.881, "valence": 0.792, "danceability": 0.438, "tempo": 144.084}, {"name": "All Your Love I Miss Loving", "energy": 0.853, "valence": 0.861, "danceability": 0.478, "tempo": 129.855}, {"name": "Tin Pan Alley", "energy": 0.0968, "valence": 0.168, "danceability": 0.576, "tempo": 113.232}, {"name": "Love Struck Baby", "energy": 0.874, "valence": 0.966, "danceability": 0.548, "tempo": 172.129}, {"name": "Tell Me", "energy": 0.68, "valence": 0.961, "danceability": 0.633, "tempo": 128.479}, {"name": "Shake for Me", "energy": 0.851, "valence": 0.766, "danceability": 0.521, "tempo": 124.361}, {"name": "Live Another Day", "energy": 0.791, "valence": 0.669, "danceability": 0.428, "tempo": 121.703}]}
