{"artist": "The Charlie Daniels Band", "album": "Windows", "mbid": "e468460e-1306-47e4-8528-6d29cac9873e", "cover_path": "/covers/the_charlie_daniels_band_-_windows.jpg", "tracks": [{"name": "Still in Saigon", "energy": 0.682, "valence": 0.925, "danceability": 0.569, "tempo": 149.212}, {"name": "Ain't No Ramblers Anymore", "energy": 0.707, "valence": 0.902, "danceability": 0.65, "tempo": 109.843}, {"name": "The Lady in Red", "energy": 0.656, "valence": 0.828, "danceability": 0.722, "tempo": 127.466}, {"name": "We Had It All One Time", "energy": 0.36, "valence": 0.412, "danceability": 0.728, "tempo": 100.85}, {"name": "Partyin' Gal", "energy": 0.873, "valence": 0.806, "danceability": 0.689, "tempo": 141.755}, {"name": "Ragin' Cajun", "energy": 0.726, "valence": 0.792, "danceability": 0.722, "tempo": 125.959}, {"name": "Makes You Want to Go Home", "energy": 0.671, "valence": 0.939, "danceability": 0.735, "tempo": 129.311}, {"name": "Blowing Along With the Wind", "energy": 0.516, "valence": 0.708, "danceability": 0.701, "tempo": 106.935}, {"name": "Nashville Moon", "energy": 0.676, "valence": 0.866, "danceability": 0.706, "tempo": 147.037}, {"name": "The Universal Hand", "energy": 0.517, "valence": 0.488, "danceability": 0.539, "tempo": 144.075}]}
