{"artist": "The Beat Farmers", "album": "The Pursuit of Happiness", "mbid": "5d6d4483-c794-4951-9b08-583044fff36d", "cover_path": "/covers/the_beat_farmers_-_the_pursuit_of_happiness.jpg", "tracks": [{"name": "Hollywood Hills", "energy": 0.732, "valence": 0.311, "danceability": 0.409, "tempo": 78.249}, {"name": "Ridin'", "energy": 0.574, "valence": 0.874, "danceability": 0.476, "tempo": 140.693}, {"name": "Dark Light", "energy": 0.511, "valence": 0.523, "danceability": 0.525, "tempo": 122.375}, {"name": "Make It Last", "energy": 0.659, "valence": 0.867, "danceability": 0.493, "tempo": 87.416}, {"name": "Key to the World", "energy": 0.55, "valence": 0.59, "danceability": 0.493, "tempo": 119.302}, {"name": "God Is Here Tonight", "energy": 0.85, "valence": 0.656, "danceability": 0.418, "tempo": 155.941}, {"name": "Big Big Man", "energy": 0.59, "valence": 0.814, "danceability": 0.573, "tempo": 101.131}, {"name": "Elephant Day Parade", "energy": 0.396, "valence": 0.72, "danceability": 0.757, "tempo": 110.517}, {"name": "Rosie", "energy": 0.0952, "valence": 0.307, "danceability": 0.368, "tempo": 98.691}, {"name": "Texas", "energy": 0.82, "valence": 0.901, "danceability": 0.475, "tempo": 111.634}]}
