{"artist": "The Dead Milkmen", "album": "Beelzebubba", "mbid": "e09ef180-c72c-4f7a-bb9d-dbfbfdfea5e8", "cover_path": null, "tracks": [{"name": "Brat in the Frat", "energy": 0.66, "valence": 0.922, "danceability": 0.754, "tempo": 132.036}, {"name": "RC’s Mom", "energy": 0.656, "valence": 0.813, "danceability": 0.641, "tempo": 111.93}, {"name": "Stuart", "energy": 0.648, "valence": 0.833, "danceability": 0.541, "tempo": 129.514}, {"name": "I Walk in the Thinnest Line", "energy": 0.758, "valence": 0.77, "danceability": 0.576, "tempo": 123.159}, {"name": "Sri Lanka Sex Hotel", "energy": 0.643, "valence": 0.334, "danceability": 0.656, "tempo": 144.839}, {"name": "Bad Party", "energy": 0.726, "valence": 0.595, "danceability": 0.663, "tempo": 101.165}, {"name": "Punk Rock Girl", "energy": 0.699, "valence": 0.887, "danceability": 0.557, "tempo": 129.492}, {"name": "Bleach Boys", "energy": 0.533, "valence": 0.862, "danceability": 0.702, "tempo": 125.2}, {"name": "My Many Smells", "energy": 0.615, "valence": 0.695, "danceability": 0.465, "tempo": 112.752}, {"name": "Smokin’ Banana Peels", "energy": 0.691, "valence": 0.602, "danceability": 0.447, "tempo": 116.465}]}
