{"artist": "The Flying Machine", "album": "Down to Earth with The Flying Machine (Expanded Edition)", "mbid": "b8aefe13-e82e-41c6-b1e2-88a8c51603da", "cover_path": "/covers/the_flying_machine_-_down_to_earth_with_the_flying_machine_expanded_edition.jpg", "tracks": [{"name": "Marie Take a Chance", "energy": 0.583, "valence": 0.73, "danceability": 0.629, "tempo": 122.42}, {"name": "Waiting on the Shores of Nowhere", "energy": 0.398, "valence": 0.692, "danceability": 0.569, "tempo": 92.636}, {"name": "There She Goes", "energy": 0.483, "valence": 0.662, "danceability": 0.664, "tempo": 91.137}, {"name": "That Same Old Feeling", "energy": 0.36, "valence": 0.709, "danceability": 0.689, "tempo": 121.9}, {"name": "Send My Baby Home Again", "energy": 0.464, "valence": 0.542, "danceability": 0.488, "tempo": 114.463}, {"name": "Baby, Make It Soon", "energy": 0.538, "valence": 0.783, "danceability": 0.461, "tempo": 89.329}, {"name": "Broken-Hearted Me, Evil Hearted You", "energy": 0.668, "valence": 0.672, "danceability": 0.604, "tempo": 99.924}, {"name": "Smile a Little Smile for Me", "energy": 0.381, "valence": 0.488, "danceability": 0.616, "tempo": 89.766}, {"name": "A Thing Called Love", "energy": 0.434, "valence": 0.786, "danceability": 0.651, "tempo": 78.722}]}
