{"artist": "The Manhattan Transfer", "album": "The Christmas Album", "mbid": "986ca3c8-62e8-4c6f-87a0-52e838991ce2", "cover_path": "/covers/the_manhattan_transfer_-_the_christmas_album.jpg", "tracks": [{"name": "Snowfall", "energy": 0.311, "valence": 0.0902, "danceability": 0.101, "tempo": 67.629}, {"name": "Let It Snow, Let It Snow, Let It Snow", "energy": 0.241, "valence": 0.17, "danceability": 0.29, "tempo": 107.467}, {"name": "Santa Claus Is Coming to Town / Santa Man (medley)", "energy": 0.63, "valence": 0.682, "danceability": 0.574, "tempo": 162.463}, {"name": "The Christmas Song (Chestnuts Roasting on an Open Fire)", "energy": 0.205, "valence": 0.0784, "danceability": 0.198, "tempo": 80.744}, {"name": "Silent Night, Holy Night", "energy": 0.245, "valence": 0.0379, "danceability": 0.103, "tempo": 83.462}, {"name": "Caroling, Caroling", "energy": 0.231, "valence": 0.686, "danceability": 0.577, "tempo": 94.941}, {"name": "Happy Holiday / The Holiday Season (medley)", "energy": 0.715, "valence": 0.5, "danceability": 0.468, "tempo": 152.898}, {"name": "A Christmas Love Song", "energy": 0.241, "valence": 0.111, "danceability": 0.3, "tempo": 70.987}, {"name": "It Came Upon the Midnight Clear", "energy": 0.235, "valence": 0.0383, "danceability": 0.195, "tempo": 132.617}, {"name": "Have Yourself a Merry Little Christmas", "energy": 0.241, "valence": 0.0614, "danceability": 0.244, "tempo": 119.909}]}
