{"artist": "The Brian Setzer Orchestra", "album": "Wolfgang’s Big Night Out", "mbid": "50533bc3-45fc-450c-b281-90e67069710a", "cover_path": "/covers/the_brian_setzer_orchestra_-_wolfgangs_big_night_out.jpg", "tracks": [{"name": "Take the 5th", "energy": 0.883, "valence": 0.688, "danceability": 0.655, "tempo": 124.777}, {"name": "One More Night With You", "energy": 0.909, "valence": 0.53, "danceability": 0.696, "tempo": 107.964}, {"name": "Wolfgang’s Big Night Out", "energy": 0.742, "valence": 0.601, "danceability": 0.777, "tempo": 119.788}, {"name": "Honey Man", "energy": 0.919, "valence": 0.529, "danceability": 0.372, "tempo": 185.274}, {"name": "Yes We Can Can", "energy": 0.911, "valence": 0.854, "danceability": 0.741, "tempo": 119.725}, {"name": "Swingin’ Willie", "energy": 0.77, "valence": 0.684, "danceability": 0.596, "tempo": 159.541}, {"name": "Sabre Dance", "energy": 0.953, "valence": 0.71, "danceability": 0.484, "tempo": 171.785}, {"name": "For Lisa", "energy": 0.557, "valence": 0.384, "danceability": 0.708, "tempo": 97.723}, {"name": "Here Comes the Broad", "energy": 0.928, "valence": 0.608, "danceability": 0.542, "tempo": 199.861}, {"name": "1812 Overdrive", "energy": 0.79, "valence": 0.657, "danceability": 0.606, "tempo": 161.728}]}
