{"artist": "Various Artists", "album": "Fifty Shades of Grey: The Classical Album", "mbid": "43734aa6-79d8-4b47-a507-cb06eeabf750", "cover_path": "/covers/various_artists_-_fifty_shades_of_grey_the_classical_album.jpg", "tracks": [{"name": "Keyboard Concerto in D minor, BWV 974: II Adagio", "energy": 0.796, "valence": 0.613, "danceability": 0.722, "tempo": 93.958}, {"name": "Bachianas Brasileiras no. 5 (for soprano and 8 cellos): I. Aria (Cantilena): Adagio", "energy": 0.899, "valence": 0.704, "danceability": 0.703, "tempo": 140.042}, {"name": "La traviata: Preludio", "energy": 0.87, "valence": 0.365, "danceability": 0.494, "tempo": 90.887}, {"name": "Canon in D (1997 - remaster)", "energy": 0.124, "valence": 0.299, "danceability": 0.159, "tempo": 73.894}, {"name": "Spem in Alium", "energy": 0.87, "valence": 0.365, "danceability": 0.494, "tempo": 90.887}, {"name": "Prélude no. 4 en mi mineur, op. 28 (remasterisé en 1995)", "energy": 0.796, "valence": 0.613, "danceability": 0.722, "tempo": 93.958}, {"name": "Piano Concerto no. 2 in C minor, op. 18: II. Adagio sostenuto (excerpt)", "energy": 0.796, "valence": 0.613, "danceability": 0.722, "tempo": 93.958}, {"name": "Fantasia on a Theme by Thomas Tallis (opening) (1985 digital remaster)", "energy": 0.198, "valence": 0.315, "danceability": 0.221, "tempo": 131.886}]}
