{"artist": "Various Artists", "album": "Reggae Gold 2000", "mbid": "c1f42a16-9959-45c5-8367-0d8a0de8cd43", "cover_path": "/covers/various_artists_-_reggae_gold_2000.jpg", "tracks": [{"name": "Look", "energy": 0.838, "valence": 0.699, "danceability": 0.746, "tempo": 89.916}, {"name": "Good in Her Clothes", "energy": 0.885, "valence": 0.661, "danceability": 0.649, "tempo": 90.557}, {"name": "Cook", "energy": 0.587, "valence": 0.905, "danceability": 0.719, "tempo": 125.453}, {"name": "Hot Gal Today (Krotches remix)", "energy": 0.565, "valence": 0.791, "danceability": 0.572, "tempo": 87.521}, {"name": "What Ah Gal", "energy": 0.456, "valence": 0.59, "danceability": 0.825, "tempo": 93.051}, {"name": "Satan Strong", "energy": 0.638, "valence": 0.761, "danceability": 0.833, "tempo": 92.865}, {"name": "Magnet", "energy": 0.663, "valence": 0.793, "danceability": 0.765, "tempo": 177.501}, {"name": "They Gonna Talk", "energy": 0.614, "valence": 0.946, "danceability": 0.748, "tempo": 153.942}, {"name": "Down by the River", "energy": 0.5, "valence": 0.932, "danceability": 0.712, "tempo": 161.76}, {"name": "Psalms 23", "energy": 0.341, "valence": 0.449, "danceability": 0.332, "tempo": 115.475}]}
