{"artist": "X", "album": "Wild Gift", "mbid": "f14bdc5c-20bb-3d97-b3be-d44f13be7bda", "cover_path": "/covers/x_-_wild_gift.jpg", "tracks": [{"name": "The Once Over Twice", "energy": 0.744, "valence": 0.727, "danceability": 0.587, "tempo": 96.765}, {"name": "We’re Desperate", "energy": 0.774, "valence": 0.655, "danceability": 0.642, "tempo": 132.935}, {"name": "Adult Books", "energy": 0.54, "valence": 0.797, "danceability": 0.632, "tempo": 133.25}, {"name": "Universal Corner", "energy": 0.601, "valence": 0.585, "danceability": 0.527, "tempo": 138.151}, {"name": "I’m Coming Over", "energy": 0.878, "valence": 0.836, "danceability": 0.522, "tempo": 118.772}, {"name": "It’s Who You Know", "energy": 0.751, "valence": 0.628, "danceability": 0.503, "tempo": 103.478}, {"name": "In This House That I Call Home", "energy": 0.818, "valence": 0.88, "danceability": 0.576, "tempo": 100.571}, {"name": "Some Other Time", "energy": 0.574, "valence": 0.782, "danceability": 0.552, "tempo": 178.088}, {"name": "White Girl", "energy": 0.639, "valence": 0.648, "danceability": 0.349, "tempo": 136.426}, {"name": "Beyond and Back", "energy": 0.824, "valence": 0.566, "danceability": 0.534, "tempo": 101.076}]}
