{"artist": "ZAYN", "album": "Icarus Falls", "mbid": "da1ebcb0-276e-435b-91b3-d7dfd0f5714f", "cover_path": null, "tracks": [{"name": "Let Me", "energy": 0.566, "valence": 0.19, "danceability": 0.46, "tempo": 168.419}, {"name": "Natural", "energy": 0.482, "valence": 0.275, "danceability": 0.655, "tempo": 99.596}, {"name": "Back to Life", "energy": 0.513, "valence": 0.506, "danceability": 0.648, "tempo": 92.079}, {"name": "Common", "energy": 0.476, "valence": 0.218, "danceability": 0.633, "tempo": 134.974}, {"name": "Imprint", "energy": 0.377, "valence": 0.408, "danceability": 0.684, "tempo": 139.888}, {"name": "Stand Still", "energy": 0.373, "valence": 0.177, "danceability": 0.661, "tempo": 98.012}, {"name": "Tonight", "energy": 0.584, "valence": 0.485, "danceability": 0.644, "tempo": 121.828}, {"name": "Flight of the Stars", "energy": 0.329, "valence": 0.35, "danceability": 0.768, "tempo": 96.009}, {"name": "If I Got You", "energy": 0.54, "valence": 0.199, "danceability": 0.547, "tempo": 169.487}, {"name": "Talk to Me", "energy": 0.495, "valence": 0.433, "danceability": 0.536, "tempo": 101.123}]}
